sindapi/__init__.py
sindapi/function/__init__.py
sindapi/function/frenet.py
sindapi/function/visualize.py
sindapi/sindmap/__init__.py
sindapi/sindmap/drivable_area.py
sindapi/sindmap/map_api.py
sindapi/sindmap/pedestrian_crossing.py
sindapi/sindmap/intersection/__init__.py
sindapi/sindmap/intersection/intersection.py
sindapi/sindmap/lane/__init__.py
sindapi/sindmap/lane/lane_segment.py
sindapi/sindmap/stretch/__init__.py
sindapi/sindmap/stretch/stretch.py
sindapi/sindmap/traffic_light/__init__.py
sindapi/sindmap/traffic_light/traffic_light.py
sindapi/sindmap/utils/__init__.py
sindapi/sindmap/utils/map_primitives.py
sindapi/sindmap/utils/utils.py
sindapi/sindtrack/__init__.py
sindapi/sindtrack/data_schema.py
sindapi/sindtrack/process_raw_data.py
sindapi/sindtrack/utils/__init__.py
sindapi/sindtrack/utils/constants.py
sindapi/sindtrack/utils/utils.py
sindapi/utils/__init__.py
sindapi/utils/typing.py
sindapi-0.0.20.dist-info/METADATA
sindapi-0.0.20.dist-info/WHEEL
sindapi-0.0.20.dist-info/top_level.txt
sindapi-0.0.20.dist-info/RECORD
