Metadata-Version: 2.1
Name: sindapi
Version: 0.0.20
Summary: api for SinD dataset
Author: Helios1208
Author-email: cly020329@gmail.com
Classifier: Programming Language :: Python :: 3
Classifier: License :: OSI Approved :: MIT License
Classifier: Operating System :: OS Independent
Requires-Dist: numpy
Requires-Dist: pyyaml
